odoo10_addon_hotel-10.0.1.0.0.99.dev21-nspkg.pth
odoo/addons/hotel/README.rst
odoo/addons/hotel/__init__.py
odoo/addons/hotel/__manifest__.py
odoo/addons/hotel/LICENSE/LICENSE
odoo/addons/hotel/data/hotel-color.png
odoo/addons/hotel/data/hotel-grey.png
odoo/addons/hotel/i18n/bg.po
odoo/addons/hotel/i18n/da.po
odoo/addons/hotel/i18n/es.po
odoo/addons/hotel/i18n/fr_BE.po
odoo/addons/hotel/i18n/hr.po
odoo/addons/hotel/i18n/pt_BR.po
odoo/addons/hotel/i18n/sv.po
odoo/addons/hotel/models/__init__.py
odoo/addons/hotel/models/hotel.py
odoo/addons/hotel/report/__init__.py
odoo/addons/hotel/report/hotel_report.py
odoo/addons/hotel/security/hotel_security.xml
odoo/addons/hotel/security/ir.model.access.csv
odoo/addons/hotel/static/description/BookHotel1.png
odoo/addons/hotel/static/description/GenerateFolio.png
odoo/addons/hotel/static/description/HotelRoom1.png
odoo/addons/hotel/static/description/bed.png
odoo/addons/hotel/static/description/book.png
odoo/addons/hotel/static/description/booking.png
odoo/addons/hotel/static/description/car.png
odoo/addons/hotel/static/description/checkin.png
odoo/addons/hotel/static/description/currency.png
odoo/addons/hotel/static/description/fast-food-icons.png
odoo/addons/hotel/static/description/gym.png
odoo/addons/hotel/static/description/head.png
odoo/addons/hotel/static/description/history.png
odoo/addons/hotel/static/description/hotel1.png
odoo/addons/hotel/static/description/hotel2.png
odoo/addons/hotel/static/description/icon-book.png
odoo/addons/hotel/static/description/icon.png
odoo/addons/hotel/static/description/inc1.png
odoo/addons/hotel/static/description/inc2.png
odoo/addons/hotel/static/description/inc3.png
odoo/addons/hotel/static/description/inc4.png
odoo/addons/hotel/static/description/inc5.png
odoo/addons/hotel/static/description/inc6.png
odoo/addons/hotel/static/description/inc7.png
odoo/addons/hotel/static/description/inc8.png
odoo/addons/hotel/static/description/inc9.png
odoo/addons/hotel/static/description/key.png
odoo10_addon_hotel-10.0.1.0.0.99.dev21.dist-info/METADATA
odoo10_addon_hotel-10.0.1.0.0.99.dev21.dist-info/WHEEL
odoo10_addon_hotel-10.0.1.0.0.99.dev21.dist-info/namespace_packages.txt
odoo10_addon_hotel-10.0.1.0.0.99.dev21.dist-info/top_level.txt
odoo10_addon_hotel-10.0.1.0.0.99.dev21.dist-info/RECORD
