Metadata-Version: 2.1
Name: odoo10-addon-hotel
Version: 10.0.1.0.0.99.dev21
Summary: Hotel Management Base
Home-page: UNKNOWN
Author: Odoo Community Association (OCA), Serpent Consulting                Services Pvt. Ltd., Odoo S.A.
Author-email: support@odoo-community.org
License: AGPL-3
Platform: UNKNOWN
Classifier: Programming Language :: Python
Classifier: Framework :: Odoo
Classifier: License :: OSI Approved :: GNU Affero General Public License v3
Requires-Python: ~=2.7
Requires-Dist: odoo (<10.1dev,>=10.0)
